{"m1_w01": "/audio/words/m1_w01.mp3", "m1_w02": "/audio/words/m1_w02.mp3", "m1_w03": "/audio/words/m1_w03.mp3", "m1_w04": "/audio/words/m1_w04.mp3", "m1_w05": "/audio/words/m1_w05.mp3", "m1_w06": "/audio/words/m1_w06.mp3", "m1_w07": "/audio/words/m1_w07.mp3", "m1_w08": "/audio/words/m1_w08.mp3", "m1_w09": "/audio/words/m1_w09.mp3", "m1_w10": "/audio/words/m1_w10.mp3", "m1_w11": "/audio/words/m1_w11.mp3", "m1_w12": "/audio/words/m1_w12.mp3", "m1_w13": "/audio/words/m1_w13.mp3", "m1_w14": "/audio/words/m1_w14.mp3", "m1_w15": "/audio/words/m1_w15.mp3", "m1_w16": "/audio/words/m1_w16.mp3", "m2_w01": "/audio/words/m2_w01.mp3", "m2_w02": "/audio/words/m2_w02.mp3", "m2_w03": "/audio/words/m2_w03.mp3", "m2_w04": "/audio/words/m2_w04.mp3", "m2_w05": "/audio/words/m2_w05.mp3", "m2_w06": "/audio/words/m2_w06.mp3", "m2_w07": "/audio/words/m2_w07.mp3", "m2_w08": "/audio/words/m2_w08.mp3", "m2_w09": "/audio/words/m2_w09.mp3", "m2_w10": "/audio/words/m2_w10.mp3", "m2_w11": "/audio/words/m2_w11.mp3", "m2_w12": "/audio/words/m2_w12.mp3", "m2_w13": "/audio/words/m2_w13.mp3", "m2_w14": "/audio/words/m2_w14.mp3", "m2_w15": "/audio/words/m2_w15.mp3", "m3_w01": "/audio/words/m3_w01.mp3", "m3_w02": "/audio/words/m3_w02.mp3", "m3_w03": "/audio/words/m3_w03.mp3", "m3_w04": "/audio/words/m3_w04.mp3", "m3_w05": "/audio/words/m3_w05.mp3", "m3_w06": "/audio/words/m3_w06.mp3", "m3_w07": "/audio/words/m3_w07.mp3", "m3_w08": "/audio/words/m3_w08.mp3", "m3_w09": "/audio/words/m3_w09.mp3", "m3_w10": "/audio/words/m3_w10.mp3", "m3_w11": "/audio/words/m3_w11.mp3", "m3_w12": "/audio/words/m3_w12.mp3", "m3_w13": "/audio/words/m3_w13.mp3", "m3_w14": "/audio/words/m3_w14.mp3", "m3_w15": "/audio/words/m3_w15.mp3", "m3_w16": "/audio/words/m3_w16.mp3", "m3_w17": "/audio/words/m3_w17.mp3", "m3_w18": "/audio/words/m3_w18.mp3", "m3_w19": "/audio/words/m3_w19.mp3", "m3_w20": "/audio/words/m3_w20.mp3", "m4_w01": "/audio/words/m4_w01.mp3", "m4_w02": "/audio/words/m4_w02.mp3", "m4_w03": "/audio/words/m4_w03.mp3", "m4_w04": "/audio/words/m4_w04.mp3", "m4_w05": "/audio/words/m4_w05.mp3", "m4_w06": "/audio/words/m4_w06.mp3", "m4_w07": "/audio/words/m4_w07.mp3", "m4_w08": "/audio/words/m4_w08.mp3", "m4_w09": "/audio/words/m4_w09.mp3", "m4_w10": "/audio/words/m4_w10.mp3", "m4_w11": "/audio/words/m4_w11.mp3", "m4_w12": "/audio/words/m4_w12.mp3", "m4_w13": "/audio/words/m4_w13.mp3", "m4_w14": "/audio/words/m4_w14.mp3", "m4_w15": "/audio/words/m4_w15.mp3", "m4_w16": "/audio/words/m4_w16.mp3", "m4_w17": "/audio/words/m4_w17.mp3", "m4_w18": "/audio/words/m4_w18.mp3", "m4_w19": "/audio/words/m4_w19.mp3", "m4_w20": "/audio/words/m4_w20.mp3", "m5_w01": "/audio/words/m5_w01.mp3", "m5_w02": "/audio/words/m5_w02.mp3", "m5_w03": "/audio/words/m5_w03.mp3", "m5_w04": "/audio/words/m5_w04.mp3", "m5_w05": "/audio/words/m5_w05.mp3", "m5_w06": "/audio/words/m5_w06.mp3", "m5_w07": "/audio/words/m5_w07.mp3", "m5_w08": "/audio/words/m5_w08.mp3", "m5_w09": "/audio/words/m5_w09.mp3", "m5_w10": "/audio/words/m5_w10.mp3", "m5_w11": "/audio/words/m5_w11.mp3", "m5_w12": "/audio/words/m5_w12.mp3", "m5_w13": "/audio/words/m5_w13.mp3", "m5_w14": "/audio/words/m5_w14.mp3", "m5_w15": "/audio/words/m5_w15.mp3", "m5_w16": "/audio/words/m5_w16.mp3", "m5_w17": "/audio/words/m5_w17.mp3", "m5_w18": "/audio/words/m5_w18.mp3", "m5_w19": "/audio/words/m5_w19.mp3", "m5_w20": "/audio/words/m5_w20.mp3", "m6_w01": "/audio/words/m6_w01.mp3", "m6_w02": "/audio/words/m6_w02.mp3", "m6_w03": "/audio/words/m6_w03.mp3", "m6_w04": "/audio/words/m6_w04.mp3", "m6_w05": "/audio/words/m6_w05.mp3", "m6_w06": "/audio/words/m6_w06.mp3", "m6_w07": "/audio/words/m6_w07.mp3", "m6_w08": "/audio/words/m6_w08.mp3", "m6_w09": "/audio/words/m6_w09.mp3", "m6_w10": "/audio/words/m6_w10.mp3", "m6_w11": "/audio/words/m6_w11.mp3", "m6_w12": "/audio/words/m6_w12.mp3", "m6_w13": "/audio/words/m6_w13.mp3", "m6_w14": "/audio/words/m6_w14.mp3", "m6_w15": "/audio/words/m6_w15.mp3"}